{"type":"FeatureCollection","features":[{"type":"Feature","properties":{"NAME":"Hebden Bridge Picture House","INFORMATION":"http://www.hebdenbridgepicturehouse.co.uk/","Postcode":"HX7 8AD","Northings":"427142","Eastings":"399341","Address ":"New Road, Hebden Bridge"},"geometry":{"type":"Point","coordinates":[-2.01147,53.74066]}},{"type":"Feature","properties":{"NAME":"The Rex Cinema","INFORMATION":"http://www.nm-cinemas.co.uk/","Postcode":"HX5 0DF","Northings":"420948","Eastings":"410816","Address ":"Coronation Street, Elland"},"geometry":{"type":"Point","coordinates":[-1.837711,53.684878]}},{"type":"Feature","properties":{"NAME":"Vue Cinema Halifax","INFORMATION":"http://broad-street-plaza.co.uk/tag/vue-cinema-halifax/","Postcode":"HX1 1YQ","Northings":"425520","Eastings":"409307","Address ":"1 North Parade, Halifax"},"geometry":{"type":"Point","coordinates":[-1.860423,53.726001]}}]}